LICENSE
MANIFEST.in
README.md
package.json
setup.py
thinks_dash_mobile_dropdown/ThinksDashMobileDropdown.py
thinks_dash_mobile_dropdown/__init__.py
thinks_dash_mobile_dropdown/_imports_.py
thinks_dash_mobile_dropdown/metadata.json
thinks_dash_mobile_dropdown/package-info.json
thinks_dash_mobile_dropdown/thinks_dash_mobile_dropdown.min.js
thinks_dash_mobile_dropdown/thinks_dash_mobile_dropdown.min.js.map
thinks_dash_mobile_dropdown.egg-info/PKG-INFO
thinks_dash_mobile_dropdown.egg-info/SOURCES.txt
thinks_dash_mobile_dropdown.egg-info/dependency_links.txt
thinks_dash_mobile_dropdown.egg-info/top_level.txt