Metadata-Version: 2.1
Name: thinks-dash-mobile-dropdown
Version: 1.0.1
Summary: Dash Dropdown Component for Smartphone
Author: thinkup-sol <s_matsumoto@thinkup-sol.co.jp>
License: MIT
Classifier: Framework :: Dash
License-File: LICENSE
